[
    {
        "filename": "/gpfs/alpine/scratch/hanzt1/gen010/ssget/MM/SNAP/com-LiveJournal/com-LiveJournal.mtx",
        "problem": {
            "id": 2781,
            "group": "SNAP",
            "name": "com-LiveJournal",
            "rows": 3997962,
            "cols": 3997962,
            "nonzeros": 69362378,
            "real": true,
            "binary": true,
            "2d3d": false,
            "posdef": false,
            "psym": 1,
            "nsym": 1,
            "kind": "undirected graph with communities",
            "row_distribution": {
                "min": 1,
                "q1": 2.0,
                "median": 6.0,
                "q3": 18.0,
                "max": 14815,
                "mean": 17.349434036641669,
                "variance": 1845.315379750689,
                "skewness": 38.16043094566308,
                "kurtosis": 7227.764972517414,
                "hyperskewness": 2038444.564363094,
                "hyperflatness": 635232430.41409
            },
            "col_distribution": {
                "min": 1,
                "q1": 2.0,
                "median": 6.0,
                "q3": 18.0,
                "max": 14815,
                "mean": 17.349434036641669,
                "variance": 1845.315379750689,
                "skewness": 38.16043094566308,
                "kurtosis": 7227.764972517414,
                "hyperskewness": 2038444.564363094,
                "hyperflatness": 635232430.41409
            }
        },
        "spmv": {
            "sellp": {
                "each_repetitions_time": [
                    16207328,
                    16216300,
                    16203999,
                    16203840,
                    16163543,
                    15736629,
                    15746664,
                    15758545,
                    15755640,
                    15741266
                ],
                "storage": 4194676568,
                "time": 15973375.4,
                "completed": true
            },
            "coo": {
                "each_repetitions_time": [
                    5759139,
                    5759336,
                    5763159,
                    5763780,
                    5770412,
                    5759900,
                    5763994,
                    5758463,
                    5765844,
                    5758461
                ],
                "storage": 1109798048,
                "time": 5762248.8,
                "completed": true
            },
            "hipsp_csr": {
                "each_repetitions_time": [
                    4789607,
                    4784757,
                    4780851,
                    4792235,
                    4783681,
                    4788999,
                    4783596,
                    4781134,
                    4787686,
                    4782260
                ],
                "storage": 848340404,
                "time": 4785480.6,
                "completed": true
            }
        },
        "optimal": {
            "spmv": "hipsp_csr"
        },
        "solver": {}
    }
]