[
    {
        "filename": "/gpfs/alpine/scratch/hanzt1/gen010/ssget/MM/JGD_Relat/rel8/rel8.mtx",
        "problem": {
            "id": 2177,
            "group": "JGD_Relat",
            "name": "rel8",
            "rows": 345688,
            "cols": 12347,
            "nonzeros": 821839,
            "real": true,
            "binary": false,
            "2d3d": false,
            "posdef": false,
            "psym": 0,
            "nsym": 0,
            "kind": "combinatorial problem"
        },
        "optimal": {
            "spmv": "sellp"
        },
        "solver": {}
    }
]