[
    {
        "filename": "/gpfs/alpine/scratch/hanzt1/gen010/ssget/MM/DIMACS10/adaptive/adaptive.mtx",
        "problem": {
            "id": 2495,
            "group": "DIMACS10",
            "name": "adaptive",
            "rows": 6815744,
            "cols": 6815744,
            "nonzeros": 27248640,
            "real": true,
            "binary": true,
            "2d3d": false,
            "posdef": false,
            "psym": 1,
            "nsym": 1,
            "kind": "undirected graph",
            "row_distribution": {
                "min": 2,
                "q1": 4.0,
                "median": 4.0,
                "q3": 4.0,
                "max": 4,
                "mean": 3.9978966346153848,
                "variance": 0.002100114991764577,
                "skewness": -21.75376175627316,
                "kurtosis": 474.7578128056516,
                "hyperskewness": -10384.253400835752,
                "hyperflatness": 228137.05881575717
            },
            "col_distribution": {
                "min": 2,
                "q1": 4.0,
                "median": 4.0,
                "q3": 4.0,
                "max": 4,
                "mean": 3.9978966346153848,
                "variance": 0.002100114991764577,
                "skewness": -21.75376175627316,
                "kurtosis": 474.7578128056516,
                "hyperskewness": -10384.253400835752,
                "hyperflatness": 228137.05881575717
            }
        },
        "spmv": {
            "sellp": {
                "each_repetitions_time": [
                    794952,
                    795081,
                    793716,
                    795210,
                    793719,
                    796124,
                    795085,
                    794442,
                    795300,
                    794404
                ],
                "storage": 328859656,
                "time": 794803.3,
                "completed": true
            },
            "coo": {
                "each_repetitions_time": [
                    1530221,
                    1546943,
                    1527487,
                    1551405,
                    1527619,
                    1545679,
                    1529554,
                    1543077,
                    1520897,
                    1544687
                ],
                "storage": 435978240,
                "time": 1536756.9,
                "completed": true
            },
            "cusp_csr": {
                "each_repetitions_time": [
                    865097,
                    866401,
                    865869,
                    865478,
                    864545,
                    864111,
                    864198,
                    865997,
                    871392,
                    865220
                ],
                "storage": 354246676,
                "time": 865830.8,
                "completed": true
            }
        },
        "optimal": {
            "spmv": "sellp"
        },
        "solver": {}
    }
]