[
    {
        "filename": "/home/fh2-project-haicore-access/ci9159/.config/ssget/MM/HB/bcsstk30/bcsstk30.mtx",
        "problem": {
            "id": 52,
            "group": "HB",
            "name": "bcsstk30",
            "rows": 28924,
            "cols": 28924,
            "nonzeros": 2043492,
            "real": true,
            "binary": true,
            "2d3d": true,
            "posdef": false,
            "psym": 1,
            "nsym": 1,
            "kind": "structural problem",
            "row_distribution": {
                "min": 4,
                "q1": 50.0,
                "median": 65.0,
                "q3": 93.0,
                "max": 219,
                "mean": 70.65039413635735,
                "variance": 1006.3579306289024,
                "skewness": 0.9038502046366508,
                "kurtosis": 4.087783820371715,
                "hyperskewness": 8.740250922373808,
                "hyperflatness": 30.566802124423277
            },
            "col_distribution": {
                "min": 4,
                "q1": 50.0,
                "median": 65.0,
                "q3": 93.0,
                "max": 219,
                "mean": 70.65039413635735,
                "variance": 1006.3579306289024,
                "skewness": 0.9038502046366508,
                "kurtosis": 4.087783820371715,
                "hyperskewness": 8.740250922373808,
                "hyperflatness": 30.566802124423277
            }
        },
        "spmv": {
            "coo": {
                "storage": 32695872,
                "max_relative_norm2": 2.883472996184926e-17,
                "time": 42960.2,
                "completed": true
            },
            "csr": {
                "storage": 24748196,
                "max_relative_norm2": 1.3511026466631122e-16,
                "time": 46628.1,
                "completed": true
            },
            "csrc": {
                "storage": 24637604,
                "max_relative_norm2": 1.751830219156745e-16,
                "time": 29730.1,
                "completed": true
            },
            "csri": {
                "storage": 24748196,
                "max_relative_norm2": 1.354418499781186e-16,
                "time": 46416.6,
                "completed": true
            },
            "csrm": {
                "storage": 24637604,
                "max_relative_norm2": 1.8833235580016669e-16,
                "time": 80591.2,
                "completed": true
            },
            "ell": {
                "storage": 76012272,
                "max_relative_norm2": 3.6014833087656125e-16,
                "time": 266553.5,
                "completed": true
            },
            "hybrid": {
                "storage": 29686928,
                "max_relative_norm2": 2.036824000713662e-16,
                "time": 66103.9,
                "completed": true
            },
            "hybrid0": {
                "storage": 32233088,
                "max_relative_norm2": 1.600408624480062e-16,
                "time": 46835.3,
                "completed": true
            },
            "hybrid25": {
                "storage": 28723664,
                "max_relative_norm2": 2.5884817688548816e-16,
                "time": 80752.4,
                "completed": true
            },
            "hybrid33": {
                "storage": 28906096,
                "max_relative_norm2": 2.9796841875836759e-16,
                "time": 91940.5,
                "completed": true
            },
            "hybrid40": {
                "storage": 28906096,
                "max_relative_norm2": 2.9802016698965659e-16,
                "time": 91840.3,
                "completed": true
            },
            "hybrid60": {
                "storage": 29066464,
                "max_relative_norm2": 2.9955852663163816e-16,
                "time": 93409.3,
                "completed": true
            },
            "hybrid80": {
                "storage": 35316544,
                "max_relative_norm2": 3.3124022107169447e-16,
                "time": 153596.8,
                "completed": true
            },
            "hybridlimit0": {
                "storage": 32464480,
                "max_relative_norm2": 1.6858702125932736e-16,
                "time": 45044.9,
                "completed": true
            },
            "hybridlimit25": {
                "storage": 32464480,
                "max_relative_norm2": 1.6858702125932736e-16,
                "time": 44708.4,
                "completed": true
            },
            "hybridlimit33": {
                "storage": 32464480,
                "max_relative_norm2": 1.6858702125932736e-16,
                "time": 44964.1,
                "completed": true
            },
            "hybridminstorage": {
                "storage": 28723664,
                "max_relative_norm2": 2.5890954200100076e-16,
                "time": 81002.0,
                "completed": true
            },
            "cusp_coo": {
                "storage": 32695888,
                "max_relative_norm2": 1.8239708140125617e-16,
                "time": 43472.0,
                "completed": true
            },
            "cusp_csr": {
                "storage": 24637620,
                "max_relative_norm2": 1.9679574770524967e-16,
                "time": 27749.5,
                "completed": true
            },
            "cusp_gcoo": {
                "storage": 32695888,
                "max_relative_norm2": 1.8239708140125617e-16,
                "time": 42878.9,
                "completed": true
            },
            "cusp_gcsr": {
                "storage": 24637620,
                "max_relative_norm2": 1.9679574770524967e-16,
                "time": 27705.2,
                "completed": true
            },
            "cusp_gcsr2": {
                "storage": 24637620,
                "max_relative_norm2": 2.2733906072620198e-16,
                "time": 29383.2,
                "completed": true
            }
        },
        "optimal": {
            "spmv": "cusp_gcsr"
        }
    }
]
