[
    {
        "filename": "/scratch/shared/pnayak/matrices_suitesparse/MM/MKS/fp/fp.mtx",
        "problem": {
            "id": 1395,
            "group": "MKS",
            "name": "fp",
            "rows": 7548,
            "cols": 7548,
            "nonzeros": 834222,
            "real": true,
            "binary": false,
            "2d3d": true,
            "posdef": false,
            "psym": 0.7575174939506899,
            "nsym": 0.002912877385765126,
            "kind": "electromagnetics problem",
            "row_distribution": {
                "min": 18,
                "q1": 39.0,
                "median": 46.0,
                "q3": 75.0,
                "max": 957,
                "mean": 112.42090620031796,
                "variance": 43191.07469276642,
                "skewness": 3.0904257021555936,
                "kurtosis": 10.75075544181862,
                "hyperskewness": 37.15176795552047,
                "hyperflatness": 129.1197943543022
            },
            "col_distribution": {
                "min": 31,
                "q1": 61.0,
                "median": 79.0,
                "q3": 104.0,
                "max": 688,
                "mean": 112.42090620031796,
                "variance": 13079.896632353128,
                "skewness": 3.1965545181945496,
                "kurtosis": 12.712223990713192,
                "hyperskewness": 51.77555162740734,
                "hyperflatness": 218.45382373295724
            }
        },
        "spmv": {
            "coo": {
                "storage": 13347552,
                "time": 32248.0,
                "completed": true
            },
            "hybrid": {
                "storage": 13106016,
                "time": 36908.2,
                "completed": true
            },
            "sellp": {
                "storage": 12302952,
                "time": 424374.2,
                "completed": true
            },
            "ell": {
                "storage": 81518400,
                "time": 54506.3,
                "completed": true
            },
            "cusp_coo": {
                "storage": 0,
                "time": 112789.4,
                "completed": true
            },
            "cusp_ell": {
                "storage": 0,
                "time": 703582.4,
                "completed": true
            },
            "cusp_hybrid": {
                "storage": 0,
                "time": 124487.7,
                "completed": true
            }
        },
        "optimal": {
            "spmv": "coo"
        }
    }
]