[
    {
        "filename": "/home/fh2-project-haicore-access/ci9159/.config/ssget/MM/TSOPF/TSOPF_FS_b162_c1/TSOPF_FS_b162_c1.mtx",
        "problem": {
            "id": 2221,
            "group": "TSOPF",
            "name": "TSOPF_FS_b162_c1",
            "rows": 10798,
            "cols": 10798,
            "nonzeros": 608540,
            "real": true,
            "binary": false,
            "2d3d": false,
            "posdef": false,
            "psym": 1,
            "nsym": 1,
            "kind": "power network problem",
            "row_distribution": {
                "min": 1,
                "q1": 4.0,
                "median": 12.0,
                "q3": 78.0,
                "max": 5054,
                "mean": 56.35673272828301,
                "variance": 59430.34042096048,
                "skewness": 19.74542260910136,
                "kurtosis": 403.5710886944848,
                "hyperskewness": 8247.610877550516,
                "hyperflatness": 168565.148234543
            },
            "col_distribution": {
                "min": 1,
                "q1": 4.0,
                "median": 12.0,
                "q3": 78.0,
                "max": 5054,
                "mean": 56.35673272828301,
                "variance": 59430.34042096048,
                "skewness": 19.74542260910136,
                "kurtosis": 403.5710886944848,
                "hyperskewness": 8247.610877550516,
                "hyperflatness": 168565.148234543
            }
        },
        "spmv": {
            "coo": {
                "storage": 9736640,
                "max_relative_norm2": 1.042058417993265e-19,
                "time": 23899.0,
                "completed": true
            },
            "csr": {
                "storage": 7373324,
                "max_relative_norm2": 1.0474151201293858e-17,
                "time": 28184.4,
                "completed": true
            },
            "csrc": {
                "storage": 7345676,
                "max_relative_norm2": 7.528095914030585e-17,
                "time": 60405.0,
                "completed": true
            },
            "csri": {
                "storage": 7373324,
                "max_relative_norm2": 1.0474151218258367e-17,
                "time": 28928.6,
                "completed": true
            },
            "csrm": {
                "storage": 7345676,
                "max_relative_norm2": 1.3949812947514638e-16,
                "time": 54359.6,
                "completed": true
            },
            "ell": {
                "storage": 654877104,
                "max_relative_norm2": 1.836270538195582e-16,
                "time": 102607.6,
                "completed": true
            },
            "hybrid": {
                "storage": 9565152,
                "max_relative_norm2": 1.3990687366929693e-16,
                "time": 26585.2,
                "completed": true
            },
            "hybrid0": {
                "storage": 9693448,
                "max_relative_norm2": 1.492263676499487e-16,
                "time": 25284.9,
                "completed": true
            },
            "hybrid25": {
                "storage": 9565152,
                "max_relative_norm2": 1.399068659484984e-16,
                "time": 26439.8,
                "completed": true
            },
            "hybrid33": {
                "storage": 9565152,
                "max_relative_norm2": 1.3990686725444968e-16,
                "time": 26375.9,
                "completed": true
            },
            "hybrid40": {
                "storage": 9565152,
                "max_relative_norm2": 1.3990687890198324e-16,
                "time": 26841.9,
                "completed": true
            },
            "hybrid60": {
                "storage": 13046160,
                "max_relative_norm2": 2.0685901966074902e-16,
                "time": 63314.5,
                "completed": true
            },
            "hybrid80": {
                "storage": 15192320,
                "max_relative_norm2": 2.0686190051281659e-16,
                "time": 70917.8,
                "completed": true
            },
            "hybridlimit0": {
                "storage": 9693448,
                "max_relative_norm2": 1.4922636562936889e-16,
                "time": 24646.6,
                "completed": true
            },
            "hybridlimit25": {
                "storage": 9693448,
                "max_relative_norm2": 1.4922636253198043e-16,
                "time": 25107.6,
                "completed": true
            },
            "hybridlimit33": {
                "storage": 9693448,
                "max_relative_norm2": 1.4922634435244544e-16,
                "time": 24716.6,
                "completed": true
            },
            "hybridminstorage": {
                "storage": 9565152,
                "max_relative_norm2": 1.399068667409255e-16,
                "time": 27744.3,
                "completed": true
            },
            "sellp": {
                "storage": 13738392,
                "max_relative_norm2": 2.0686182601021342e-16,
                "time": 1075947.4,
                "completed": true
            },
            "cusp_coo": {
                "storage": 9736656,
                "max_relative_norm2": 1.5846996671483028e-16,
                "time": 25094.3,
                "completed": true
            },
            "cusp_csr": {
                "storage": 7345692,
                "max_relative_norm2": 1.4589515800458677e-16,
                "time": 242022.9,
                "completed": true
            },
            "cusp_gcoo": {
                "storage": 9736656,
                "max_relative_norm2": 1.5846996671470374e-16,
                "time": 24929.4,
                "completed": true
            },
            "cusp_gcsr": {
                "storage": 7345692,
                "max_relative_norm2": 1.4589515800458677e-16,
                "time": 241828.5,
                "completed": true
            },
            "cusp_gcsr2": {
                "storage": 7345692,
                "max_relative_norm2": 1.4589515800458677e-16,
                "time": 242188.1,
                "completed": true
            }
        },
        "optimal": {
            "spmv": "coo"
        }
    }
]
