[
    {
        "filename": "/home/benchmarks/.config/ssget/MM/AG-Monien/debr/debr.mtx",
        "problem": {
            "id": 2439,
            "group": "AG-Monien",
            "name": "debr",
            "rows": 1048576,
            "cols": 1048576,
            "nonzeros": 4194298,
            "real": true,
            "binary": true,
            "2d3d": false,
            "posdef": false,
            "psym": 1,
            "nsym": 1,
            "kind": "undirected graph sequence",
            "row_distribution": {
                "min": 2,
                "q1": 4.0,
                "median": 4.0,
                "q3": 4.0,
                "max": 4,
                "mean": 3.9999942779541017,
                "variance": 0.000009536710422253237,
                "skewness": -582.8684613276236,
                "kurtosis": 356513.96800354306,
                "hyperskewness": -224099626.20816917,
                "hyperflatness": 142935492397.816
            },
            "col_distribution": {
                "min": 2,
                "q1": 4.0,
                "median": 4.0,
                "q3": 4.0,
                "max": 4,
                "mean": 3.9999942779541017,
                "variance": 0.000009536710422253237,
                "skewness": -582.8684613276236,
                "kurtosis": 356513.96800354306,
                "hyperskewness": -224099626.20816917,
                "hyperflatness": 142935492397.816
            }
        },
        "spmv": {
            "csr": {
                "storage": 54525884,
                "time": 721463.1,
                "completed": true
            },
            "coo": {
                "storage": 67108768,
                "time": 994523.9,
                "completed": true
            },
            "hybrid": {
                "storage": 50331648,
                "time": 578695.5,
                "completed": true
            },
            "sellp": {
                "storage": 50593800,
                "time": 618539.9,
                "completed": true
            },
            "ell": {
                "storage": 50331648,
                "time": 577052.4,
                "completed": true
            }
        },
        "optimal": {
            "spmv": "ell"
        }
    }
]