[
    {
        "filename": "/home/users/coe0256/.config/ssget/MM/Sandia/fpga_trans_02/fpga_trans_02.mtx",
        "problem": {
            "id": 1107,
            "group": "Sandia",
            "name": "fpga_trans_02",
            "rows": 1220,
            "cols": 1220,
            "nonzeros": 7382,
            "real": true,
            "binary": false,
            "2d3d": false,
            "posdef": false,
            "psym": 1,
            "nsym": 0.2138728323699422,
            "kind": "subsequent circuit simulation problem",
            "row_distribution": {
                "min": 1,
                "q1": 4.0,
                "median": 5.0,
                "q3": 5.0,
                "max": 50,
                "mean": 6.050819672131148,
                "variance": 34.94987637731793,
                "skewness": 5.046202501817653,
                "kurtosis": 33.5778684238928,
                "hyperskewness": 229.60412948949833,
                "hyperflatness": 1591.2929398159466
            },
            "col_distribution": {
                "min": 1,
                "q1": 4.0,
                "median": 5.0,
                "q3": 5.0,
                "max": 50,
                "mean": 6.050819672131148,
                "variance": 34.94987637731793,
                "skewness": 5.046202501817653,
                "kurtosis": 33.5778684238928,
                "hyperskewness": 229.60412948949833,
                "hyperflatness": 1591.2929398159466
            }
        },
        "spmv": {
            "coo": {
                "storage": 118112,
                "max_relative_norm2": 0.0,
                "time": 37173.7,
                "completed": true
            },
            "csr": {
                "storage": 93932,
                "max_relative_norm2": 8.074597689008789e-17,
                "time": 38680.8,
                "completed": true
            },
            "csrc": {
                "storage": 93468,
                "max_relative_norm2": 8.074597689008789e-17,
                "time": 38580.6,
                "completed": true
            },
            "csri": {
                "storage": 93932,
                "max_relative_norm2": 0.0,
                "time": 43125.8,
                "completed": true
            },
            "csrm": {
                "storage": 93468,
                "max_relative_norm2": 8.983781110762685e-17,
                "time": 63138.5,
                "completed": true
            },
            "ell": {
                "storage": 732000,
                "max_relative_norm2": 1.3249650217566924e-16,
                "time": 39092.6,
                "completed": true
            },
            "hybrid": {
                "storage": 113232,
                "max_relative_norm2": 8.307689028047446e-17,
                "time": 41709.6,
                "completed": true
            },
            "hybrid0": {
                "storage": 113232,
                "max_relative_norm2": 9.327293024548055e-17,
                "time": 41016.7,
                "completed": true
            },
            "hybrid25": {
                "storage": 102928,
                "max_relative_norm2": 1.0287424889493058e-16,
                "time": 43708.8,
                "completed": true
            },
            "hybrid33": {
                "storage": 102928,
                "max_relative_norm2": 1.0340241205356373e-16,
                "time": 43540.5,
                "completed": true
            },
            "hybrid40": {
                "storage": 105264,
                "max_relative_norm2": 1.0037746152110137e-16,
                "time": 44247.5,
                "completed": true
            },
            "hybrid60": {
                "storage": 105264,
                "max_relative_norm2": 1.0041137393104486e-16,
                "time": 44635.7,
                "completed": true
            },
            "hybrid80": {
                "storage": 105264,
                "max_relative_norm2": 1.0024169715353224e-16,
                "time": 44763.7,
                "completed": true
            },
            "hybridlimit0": {
                "storage": 118112,
                "max_relative_norm2": 0.0,
                "time": 38635.9,
                "completed": true
            },
            "hybridlimit25": {
                "storage": 118112,
                "max_relative_norm2": 0.0,
                "time": 39162.9,
                "completed": true
            },
            "hybridlimit33": {
                "storage": 118112,
                "max_relative_norm2": 0.0,
                "time": 38225.8,
                "completed": true
            },
            "hybridminstorage": {
                "storage": 102928,
                "max_relative_norm2": 1.0287424889493058e-16,
                "time": 43479.4,
                "completed": true
            },
            "sellp": {
                "storage": 194632,
                "max_relative_norm2": 1.1045373637340398e-16,
                "time": 76123.2,
                "completed": true
            },
            "hipsp_coo": {
                "storage": 16,
                "max_relative_norm2": 1.0100755857371975e-16,
                "time": 48728.7,
                "completed": true
            },
            "hipsp_csr": {
                "storage": 93484,
                "max_relative_norm2": 1.0613035240911922e-16,
                "time": 45024.7,
                "completed": true
            },
            "hipsp_ell": {
                "completed": false
            },
            "hipsp_hybrid": {
                "storage": 16,
                "max_relative_norm2": 1.062312824175217e-16,
                "time": 59393.3,
                "completed": true
            }
        },
        "optimal": {
            "spmv": "coo"
        }
    }
]
