[
    {
        "filename": "/gpfs/alpine/scratch/hanzt1/gen010/ssget/MM/Mittelmann/pds-30/pds-30.mtx",
        "problem": {
            "id": 1646,
            "group": "Mittelmann",
            "name": "pds-30",
            "rows": 49944,
            "cols": 158489,
            "nonzeros": 340635,
            "real": true,
            "binary": false,
            "2d3d": false,
            "posdef": false,
            "psym": 0,
            "nsym": 0,
            "kind": "linear programming problem"
        },
        "optimal": {
            "spmv": "coo"
        },
        "spmv": {
            "sellp": {
                "each_repetitions_time": [
                    100364,
                    98628,
                    98048,
                    98051,
                    97882,
                    98915,
                    100641,
                    97487,
                    98708,
                    97605,
                    98749,
                    97626,
                    98046,
                    98355,
                    98073,
                    98553,
                    98529,
                    98786,
                    97521,
                    98593,
                    100229,
                    99088,
                    98589,
                    97414,
                    97799,
                    98859,
                    98432,
                    99761,
                    98650,
                    98285,
                    97770,
                    98324,
                    98111,
                    98467,
                    99496,
                    97209,
                    98423,
                    97283,
                    99297,
                    98111,
                    98947,
                    98167,
                    98713,
                    97861,
                    98857,
                    98015,
                    98508,
                    98237,
                    97683,
                    97320,
                    98591,
                    98129,
                    98665,
                    98250,
                    98381,
                    98055,
                    98591,
                    98113,
                    98650,
                    97554,
                    98462,
                    97703,
                    98697,
                    98075,
                    99516,
                    98048,
                    98588,
                    97969,
                    98946,
                    98962,
                    98752,
                    98779,
                    97807,
                    97718,
                    98429,
                    97621,
                    98605,
                    98672,
                    98687,
                    98162,
                    97974,
                    98286,
                    99169,
                    97541,
                    98462,
                    97349,
                    98090,
                    98814,
                    98625,
                    99075,
                    98759,
                    98116,
                    98545,
                    98386,
                    97669,
                    98084,
                    98562,
                    98092,
                    97761,
                    97415
                ],
                "storage": 16566744,
                "time": 98370.16,
                "completed": true
            },
            "cusp_csr": {
                "each_repetitions_time": [
                    36510,
                    36373,
                    36376,
                    37084,
                    36528,
                    37419,
                    37405,
                    37656,
                    36974,
                    38178,
                    37123,
                    38229,
                    37231,
                    37149,
                    37145,
                    36360,
                    36272,
                    38145,
                    37608,
                    37348,
                    37162,
                    37485,
                    36339,
                    37406,
                    36684,
                    38831,
                    36362,
                    36903,
                    36397,
                    37084,
                    37145,
                    37155,
                    37002,
                    36069,
                    36450,
                    36543,
                    37428,
                    37131,
                    36575,
                    36950,
                    35854,
                    37090,
                    37260,
                    37178,
                    36110,
                    37241,
                    37096,
                    36973,
                    36752,
                    37111,
                    37108,
                    37131,
                    36705,
                    37465,
                    36697,
                    36018,
                    37674,
                    36311,
                    36042,
                    36503,
                    37168,
                    36565,
                    36957,
                    37078,
                    36411,
                    38297,
                    36978,
                    36905,
                    37340,
                    37137,
                    37145,
                    36202,
                    37129,
                    38070,
                    36093,
                    37027,
                    35835,
                    38118,
                    37247,
                    37313,
                    37107,
                    37502,
                    36270,
                    37190,
                    36293,
                    36400,
                    37108,
                    37856,
                    37789,
                    37131,
                    37193,
                    37033,
                    36904,
                    37120,
                    37292,
                    37126,
                    36612,
                    36571,
                    36400,
                    36384
                ],
                "storage": 4287416,
                "time": 36988.29,
                "completed": true
            },
            "coo": {
                "each_repetitions_time": [
                    31203,
                    31163,
                    31698,
                    31043,
                    31171,
                    31698,
                    31245,
                    30944,
                    31098,
                    30711,
                    31829,
                    30720,
                    31368,
                    30718,
                    31328,
                    30795,
                    31532,
                    31985,
                    31028,
                    30965,
                    32022,
                    30949,
                    31089,
                    30807,
                    31122,
                    31204,
                    31249,
                    31649,
                    31114,
                    31154,
                    31317,
                    30830,
                    31344,
                    30846,
                    31067,
                    31323,
                    30932,
                    31074,
                    32032,
                    31116,
                    31549,
                    31600,
                    30923,
                    30799,
                    31118,
                    30969,
                    31801,
                    30901,
                    31198,
                    30838,
                    31382,
                    30614,
                    31237,
                    31379,
                    31036,
                    30702,
                    31217,
                    31046,
                    31122,
                    31125,
                    31263,
                    30877,
                    31057,
                    30758,
                    31047,
                    30704,
                    31800,
                    30720,
                    31012,
                    31071,
                    31253,
                    30795,
                    31440,
                    31244,
                    31014,
                    30729,
                    31065,
                    31038,
                    31044,
                    30834,
                    31184,
                    30769,
                    31823,
                    30823,
                    30940,
                    31175,
                    31035,
                    30645,
                    31141,
                    30756,
                    31858,
                    30932,
                    31239,
                    30251,
                    31020,
                    30941,
                    31156,
                    30667,
                    31231,
                    30993
                ],
                "storage": 5450160,
                "time": 31123.82,
                "completed": true
            }
        },
        "solver": {}
    }
]