[
    {
        "filename": "/home/u45533/.config/ssget/MM/Rajat/rajat28/rajat28.mtx",
        "problem": {
            "id": 1377,
            "group": "Rajat",
            "name": "rajat28",
            "rows": 87190,
            "cols": 87190,
            "nonzeros": 606489,
            "real": true,
            "binary": false,
            "2d3d": false,
            "posdef": false,
            "psym": 0.9906572831072956,
            "nsym": 0.1072533437604223,
            "kind": "circuit simulation problem",
            "row_distribution": {
                "min": 1,
                "q1": 4.0,
                "median": 5.0,
                "q3": 8.0,
                "max": 29105,
                "mean": 6.96450280995527,
                "variance": 10399.394484874383,
                "skewness": 269.29901444962106,
                "kurtosis": 76196.83599387374,
                "hyperskewness": 21703979.708073345,
                "hyperflatness": 6190648597.553332
            },
            "col_distribution": {
                "min": 1,
                "q1": 4.0,
                "median": 5.0,
                "q3": 8.0,
                "max": 29105,
                "mean": 6.96450280995527,
                "variance": 10394.65472114001,
                "skewness": 269.4704415090734,
                "kurtosis": 76266.05079136782,
                "hyperskewness": 21728723.523800509,
                "hyperflatness": 6199120786.420773
            }
        },
        "spmv": {
            "coo": {
                "storage": 9703824,
                "max_relative_norm2": 0.0,
                "time": 1246506.9,
                "completed": true
            },
            "csr": {
                "storage": 7632008,
                "max_relative_norm2": 2.4381513560333368e-16,
                "time": 1298419.8,
                "completed": true
            },
            "csrc": {
                "storage": 7626632,
                "max_relative_norm2": 8.173648207969299e-17,
                "time": 2041275.0,
                "completed": true
            },
            "csri": {
                "storage": 7632008,
                "max_relative_norm2": 2.4381513575391338e-16,
                "time": 1298756.3,
                "completed": true
            },
            "sellp": {
                "storage": 64423992,
                "max_relative_norm2": 4.608774387554422e-16,
                "time": 22705026.7,
                "completed": true
            },
            "onemkl_csr": {
                "storage": 7626632,
                "max_relative_norm2": 2.613832680871837e-16,
                "time": 3784907.3,
                "completed": true
            }
        },
        "optimal": {
            "spmv": "coo"
        }
    }
]
