[
    {
        "filename": "/gpfs/alpine/scratch/hanzt1/gen010/ssget/MM/vanHeukelum/cage9/cage9.mtx",
        "problem": {
            "id": 910,
            "group": "vanHeukelum",
            "name": "cage9",
            "rows": 3534,
            "cols": 3534,
            "nonzeros": 41594,
            "real": true,
            "binary": false,
            "2d3d": false,
            "posdef": false,
            "psym": 1,
            "nsym": 0.1535470310036784,
            "kind": "directed weighted graph",
            "row_distribution": {
                "min": 3,
                "q1": 9.0,
                "median": 12.0,
                "q3": 14.0,
                "max": 23,
                "mean": 11.76966610073571,
                "variance": 14.07654448386984,
                "skewness": 0.30966203122140226,
                "kurtosis": 2.8622815680596584,
                "hyperskewness": 2.6555884095358328,
                "hyperflatness": 12.993422669705602
            },
            "col_distribution": {
                "min": 3,
                "q1": 9.0,
                "median": 12.0,
                "q3": 14.0,
                "max": 23,
                "mean": 11.76966610073571,
                "variance": 14.07654448386984,
                "skewness": 0.30966203122140226,
                "kurtosis": 2.8622815680596584,
                "hyperskewness": 2.6555884095358328,
                "hyperflatness": 12.993422669705602
            }
        },
        "spmv": {
            "coo": {
                "storage": 665504,
                "time": 25209.4,
                "completed": true
            },
            "csr": {
                "storage": 518388,
                "time": 20194.3,
                "completed": true
            },
            "cusp_csr": {
                "storage": 513284,
                "time": 18693.0,
                "completed": true
            },
            "cusp_coo": {
                "storage": 16,
                "time": 39690.9,
                "completed": true
            },
            "cusp_gcsr": {
                "storage": 513284,
                "time": 18596.9,
                "completed": true
            },
            "cusp_gcsr2": {
                "storage": 513284,
                "time": 18590.5,
                "completed": true
            }
        },
        "optimal": {
            "spmv": "cusp_gcsr2"
        }
    }
]