[
    {
        "filename": "/home/users/coe0256/.config/ssget/MM/Meszaros/deter1/deter1.mtx",
        "problem": {
            "id": 1795,
            "group": "Meszaros",
            "name": "deter1",
            "rows": 5527,
            "cols": 15737,
            "nonzeros": 32187,
            "real": true,
            "binary": false,
            "2d3d": false,
            "posdef": false,
            "psym": 0,
            "nsym": 0,
            "kind": "linear programming problem",
            "row_distribution": {
                "min": 2,
                "q1": 4.0,
                "median": 4.0,
                "q3": 4.0,
                "max": 30,
                "mean": 5.82359326940474,
                "variance": 42.59833606616008,
                "skewness": 3.363945154388924,
                "kurtosis": 12.463666988578949,
                "hyperskewness": 46.02028174000483,
                "hyperflatness": 170.27936533285198
            },
            "col_distribution": {
                "min": 1,
                "q1": 2.0,
                "median": 2.0,
                "q3": 2.0,
                "max": 53,
                "mean": 2.045307237720023,
                "variance": 2.480440740897611,
                "skewness": 32.27864348012658,
                "kurtosis": 1044.356125694544,
                "hyperskewness": 33788.43722621308,
                "hyperflatness": 1093170.4165397466
            }
        },
        "spmv": {
            "coo": {
                "storage": 514992,
                "max_relative_norm2": 0.0,
                "time": 45058.7,
                "completed": true
            },
            "csr": {
                "storage": 410368,
                "max_relative_norm2": 8.452550932736877e-17,
                "time": 39728.8,
                "completed": true
            },
            "csrc": {
                "storage": 408356,
                "max_relative_norm2": 8.452550932736877e-17,
                "time": 39610.7,
                "completed": true
            },
            "csri": {
                "storage": 410368,
                "max_relative_norm2": 0.0,
                "time": 40464.6,
                "completed": true
            },
            "csrm": {
                "storage": 408356,
                "max_relative_norm2": 1.1988723293095732e-16,
                "time": 61588.4,
                "completed": true
            },
            "ell": {
                "storage": 1989720,
                "max_relative_norm2": 1.419960563015421e-16,
                "time": 59464.6,
                "completed": true
            },
            "hybrid": {
                "storage": 426944,
                "max_relative_norm2": 1.0719865107192589e-16,
                "time": 47625.7,
                "completed": true
            },
            "hybrid0": {
                "storage": 470776,
                "max_relative_norm2": 9.35179229243392e-17,
                "time": 49120.5,
                "completed": true
            },
            "hybrid25": {
                "storage": 426944,
                "max_relative_norm2": 1.0654666677196155e-16,
                "time": 47384.5,
                "completed": true
            },
            "hybrid33": {
                "storage": 426944,
                "max_relative_norm2": 1.0724866535497174e-16,
                "time": 47623.6,
                "completed": true
            },
            "hybrid40": {
                "storage": 426944,
                "max_relative_norm2": 1.0637492639957514e-16,
                "time": 47947.5,
                "completed": true
            },
            "hybrid60": {
                "storage": 426944,
                "max_relative_norm2": 1.070780509101764e-16,
                "time": 47314.7,
                "completed": true
            },
            "hybrid80": {
                "storage": 426944,
                "max_relative_norm2": 1.0647942352519561e-16,
                "time": 47675.7,
                "completed": true
            },
            "hybridlimit0": {
                "storage": 514992,
                "max_relative_norm2": 0.0,
                "time": 46769.5,
                "completed": true
            },
            "hybridlimit25": {
                "storage": 514992,
                "max_relative_norm2": 0.0,
                "time": 46753.8,
                "completed": true
            },
            "hybridlimit33": {
                "storage": 514992,
                "max_relative_norm2": 0.0,
                "time": 46155.6,
                "completed": true
            },
            "hybridminstorage": {
                "storage": 426944,
                "max_relative_norm2": 1.0595726603927282e-16,
                "time": 47475.6,
                "completed": true
            },
            "sellp": {
                "storage": 2005880,
                "max_relative_norm2": 1.419960563015421e-16,
                "time": 60488.5,
                "completed": true
            },
            "hipsp_coo": {
                "storage": 16,
                "max_relative_norm2": 7.868909449193188e-17,
                "time": 53997.4,
                "completed": true
            },
            "hipsp_csr": {
                "storage": 408372,
                "max_relative_norm2": 9.611956945421605e-17,
                "time": 53816.5,
                "completed": true
            },
            "hipsp_ell": {
                "completed": false
            },
            "hipsp_hybrid": {
                "storage": 16,
                "max_relative_norm2": 1.149740347280118e-16,
                "time": 56301.4,
                "completed": true
            }
        },
        "optimal": {
            "spmv": "csrc"
        }
    }
]
