[
    {
        "filename": "/gpfs/alpine/scratch/hanzt1/gen010/ssget/MM/Nemeth/nemeth13/nemeth13.mtx",
        "problem": {
            "id": 777,
            "group": "Nemeth",
            "name": "nemeth13",
            "rows": 9506,
            "cols": 9506,
            "nonzeros": 474472,
            "real": true,
            "binary": false,
            "2d3d": false,
            "posdef": false,
            "psym": 1,
            "nsym": 1,
            "kind": "subsequent theoretical/quantum chemistry problem",
            "row_distribution": {
                "min": 21,
                "q1": 49.0,
                "median": 51.0,
                "q3": 56.0,
                "max": 59,
                "mean": 49.91289711760993,
                "variance": 49.28107288170394,
                "skewness": -1.014082547839385,
                "kurtosis": 2.952103456911894,
                "hyperskewness": -5.371828096449281,
                "hyperflatness": 13.024857728644296
            },
            "col_distribution": {
                "min": 21,
                "q1": 49.0,
                "median": 51.0,
                "q3": 56.0,
                "max": 59,
                "mean": 49.91289711760993,
                "variance": 49.28107288170394,
                "skewness": -1.014082547839385,
                "kurtosis": 2.952103456911894,
                "hyperskewness": -5.371828096449281,
                "hyperflatness": 13.024857728644296
            }
        },
        "spmv": {
            "sellp": {
                "storage": 6681688,
                "time": 61491.6,
                "completed": true
            }
        },
        "optimal": {
            "spmv": "sellp"
        },
        "solver": {
            "gmres": {
                "recurrent_residuals": [],
                "true_residuals": [],
                "rhs_norm": 10.479984730103814,
                "generate": {
                    "components": {},
                    "time": 12214.2
                },
                "apply": {
                    "components": {},
                    "iterations": 16,
                    "time": 5333264.2
                },
                "residual_norm": 0.0000964354229108167,
                "completed": true
            },
            "cg": {
                "recurrent_residuals": [],
                "true_residuals": [],
                "rhs_norm": 10.479984730103814,
                "generate": {
                    "components": {},
                    "time": 11330.4
                },
                "apply": {
                    "components": {},
                    "iterations": 20,
                    "time": 3598283.2
                },
                "residual_norm": 0.000003992163760612225,
                "completed": true
            },
            "bicgstab": {
                "recurrent_residuals": [],
                "true_residuals": [],
                "rhs_norm": 10.479984730103814,
                "generate": {
                    "components": {},
                    "time": 11439.2
                },
                "apply": {
                    "components": {},
                    "iterations": 27,
                    "time": 4888128.0
                },
                "residual_norm": 0.000006009543086508366,
                "completed": true
            }
        }
    }
]