[
    {
        "filename": "/gpfs/alpine/scratch/hanzt1/csc336/ssget/MM/LPnetlib/lp_beaconfd/lp_beaconfd.mtx",
        "problem": {
            "id": 602,
            "group": "LPnetlib",
            "name": "lp_beaconfd",
            "rows": 173,
            "cols": 295,
            "nonzeros": 3408,
            "real": true,
            "binary": false,
            "2d3d": false,
            "posdef": false,
            "psym": 0,
            "nsym": 0,
            "kind": "linear programming problem",
            "row_distribution": {
                "min": 1,
                "q1": 2.0,
                "median": 3.0,
                "q3": 16.5,
                "max": 154,
                "mean": 19.69942196531792,
                "variance": 1137.898092151425,
                "skewness": 2.048494695202829,
                "kurtosis": 6.570407149228712,
                "hyperskewness": 21.774502431431658,
                "hyperflatness": 77.38246011102581
            },
            "col_distribution": {
                "min": 1,
                "q1": 1.0,
                "median": 15.0,
                "q3": 22.0,
                "max": 27,
                "mean": 11.552542372881357,
                "variance": 102.83706980752712,
                "skewness": 0.06566029734372625,
                "kurtosis": 1.1645462160328988,
                "hyperskewness": 0.2630630530174189,
                "hyperflatness": 1.489327574963879
            }
        },
        "spmv": {
            "csr": {
                "storage": 42020,
                "time": 32607.1,
                "completed": true
            },
            "csri": {
                "storage": 42020,
                "time": 32176.4,
                "completed": true
            },
            "csrm": {
                "storage": 41592,
                "time": 99057.5,
                "completed": true
            },
            "csrc": {
                "storage": 41592,
                "time": 38865.9,
                "completed": true
            },
            "coo": {
                "storage": 54528,
                "time": 30567.0,
                "completed": true
            },
            "hybrid": {
                "storage": 54528,
                "time": 40469.1,
                "completed": true
            },
            "sellp": {
                "storage": 211256,
                "time": 76743.0,
                "completed": true
            },
            "ell": {
                "storage": 319704,
                "time": 30964.0,
                "completed": true
            },
            "cusp_coo": {
                "storage": 16,
                "time": 49075.0,
                "completed": true
            },
            "cusp_ell": {
                "storage": 16,
                "time": 84116.7,
                "completed": true
            },
            "cusp_hybrid": {
                "storage": 16,
                "time": 48617.7,
                "completed": true
            },
            "cusp_csr": {
                "storage": 41608,
                "time": 33096.6,
                "completed": true
            },
            "cusp_csrmp": {
                "storage": 41608,
                "time": 111007.1,
                "completed": true
            },
            "cusp_csrex": {
                "storage": 41592,
                "time": 53257.1,
                "completed": true
            },
            "cusp_csrmm": {
                "storage": 41608,
                "time": 33545.7,
                "completed": true
            }
        },
        "optimal": {
            "spmv": "coo"
        }
    }
]